COPYING
MANIFEST.in
Makefile
README
TODO
setup.py
auxtools/htmlmerge.py
custom_2to3/__init__.py
custom_2to3/fix_docstrings.py
custom_2to3/fix_rename_unicode.py
doc/Makefile
examples/check_version.py
examples/echobot.py
examples/roster.py
examples/send_message_client.py
examples/simple_send_message.py
pyxmpp2/__init__.py
pyxmpp2/binding.py
pyxmpp2/cache.py
pyxmpp2/cert.py
pyxmpp2/client.py
pyxmpp2/clientstream.py
pyxmpp2/constants.py
pyxmpp2/error.py
pyxmpp2/etree.py
pyxmpp2/exceptions.py
pyxmpp2/expdict.py
pyxmpp2/interfaces.py
pyxmpp2/iq.py
pyxmpp2/jid.py
pyxmpp2/message.py
pyxmpp2/presence.py
pyxmpp2/resolver.py
pyxmpp2/roster.py
pyxmpp2/session.py
pyxmpp2/settings.py
pyxmpp2/simple.py
pyxmpp2/stanza.py
pyxmpp2/stanzapayload.py
pyxmpp2/stanzaprocessor.py
pyxmpp2/streambase.py
pyxmpp2/streamevents.py
pyxmpp2/streamsasl.py
pyxmpp2/streamtls.py
pyxmpp2/transport.py
pyxmpp2/utils.py
pyxmpp2/version.py
pyxmpp2/xmppparser.py
pyxmpp2/xmppserializer.py
pyxmpp2/xmppstringprep.py
pyxmpp2.egg-info/PKG-INFO
pyxmpp2.egg-info/SOURCES.txt
pyxmpp2.egg-info/dependency_links.txt
pyxmpp2.egg-info/requires.txt
pyxmpp2.egg-info/top_level.txt
pyxmpp2/ext/__init__.py
pyxmpp2/ext/component.py
pyxmpp2/ext/dataforms.py
pyxmpp2/ext/delay.py
pyxmpp2/ext/disco.py
pyxmpp2/ext/legacyauth.py
pyxmpp2/ext/register.py
pyxmpp2/ext/vcard.py
pyxmpp2/ext/version.py
pyxmpp2/mainloop/__init__.py
pyxmpp2/mainloop/base.py
pyxmpp2/mainloop/events.py
pyxmpp2/mainloop/glib.py
pyxmpp2/mainloop/interfaces.py
pyxmpp2/mainloop/poll.py
pyxmpp2/mainloop/select.py
pyxmpp2/mainloop/threads.py
pyxmpp2/mainloop/tornado.py
pyxmpp2/mainloop/wait.py
pyxmpp2/sasl/__init__.py
pyxmpp2/sasl/core.py
pyxmpp2/sasl/digest_md5.py
pyxmpp2/sasl/external.py
pyxmpp2/sasl/gssapi.py
pyxmpp2/sasl/plain.py
pyxmpp2/sasl/saslprep.py
pyxmpp2/sasl/scram.py
pyxmpp2/sasl/xfacebookplatform.py
pyxmpp2/server/__init__.py
pyxmpp2/server/listener.py
pyxmpp2/test/__init__.py
pyxmpp2/test/__main__.py
pyxmpp2/test/_support.py
pyxmpp2/test/_util.py
pyxmpp2/test/binding.py
pyxmpp2/test/cert.py
pyxmpp2/test/ext_version.py
pyxmpp2/test/iq.py
pyxmpp2/test/jid.py
pyxmpp2/test/message.py
